CHANGELOG.rst
CONTRIBUTING.rst
LICENSE.txt
MANIFEST.in
README.rst
setup.py
bin/benchmark_pydy_code_gen.py
bin/time_rhs.py
docs/Makefile
docs/changelog.rst
docs/codegen.rst
docs/conf.py
docs/index-opening.txt
docs/index.rst
docs/install.rst
docs/models.rst
docs/readme-msd-result.png
docs/rtd-env.yml
docs/system.rst
docs/tutorials.rst
docs/usage.rst
docs/utils.rst
docs/examples/3d-n-body-pendulum.rst
docs/examples/astrobee.png
docs/examples/astrobee.rst
docs/examples/bicycle-coordinates.png
docs/examples/bicycle-geometry.png
docs/examples/carvallo-whipple.rst
docs/examples/chaos-pendulum.rst
docs/examples/chaos-pendulum.svg
docs/examples/kane-levinson-1985-chapter-02.rst
docs/examples/kane-levinson-1985-chapter-03.rst
docs/examples/kane-levinson-1985.png
docs/examples/mass-spring-damper.rst
docs/examples/mass_spring_damper.svg
docs/examples/multidof-holonomic.png
docs/examples/multidof-holonomic.rst
docs/examples/rocket-car.png
docs/examples/rocket-car.rst
docs/examples/rocket-car.svg
docs/examples/three-link-conical-pendulum.gif
docs/examples/three-link-conical-pendulum.rst
docs/viz/api.rst
docs/viz/javascript_api.rst
docs/viz/python_api.rst
docs/viz/viz.rst
docs/viz/images/screenshot1.png
docs/viz/images/screenshot2.png
docs/viz/images/screenshot3.png
docs/viz/images/screenshot4.png
docs/viz/images/screenshot5.png
docs/viz/jsmodules/dv.rst
docs/viz/jsmodules/param_editor.rst
docs/viz/jsmodules/parser.rst
docs/viz/jsmodules/scene.rst
docs/viz/pymodules/cameras.rst
docs/viz/pymodules/lights.rst
docs/viz/pymodules/scene.rst
docs/viz/pymodules/shapes.rst
docs/viz/pymodules/visualization_frame.rst
pydy/__init__.py
pydy/models.py
pydy/system.py
pydy/utils.py
pydy/version.py
pydy.egg-info/PKG-INFO
pydy.egg-info/SOURCES.txt
pydy.egg-info/dependency_links.txt
pydy.egg-info/requires.txt
pydy.egg-info/top_level.txt
pydy/codegen/__init__.py
pydy/codegen/c_code.py
pydy/codegen/cython_code.py
pydy/codegen/matrix_generator.py
pydy/codegen/octave_code.py
pydy/codegen/ode_function_generators.py
pydy/codegen/tests/__init__.py
pydy/codegen/tests/test_c_code.py
pydy/codegen/tests/test_cython_code.py
