Metadata-Version: 2.4
Name: pydy
Version: 0.8.0
Summary: Python tool kit for multi-body dynamics.
Home-page: http://pydy.org
Author: PyDy Authors
Author-email: pydy@googlegroups.com
License: LICENSE.txt
Keywords: multibody dynamics
Classifier: Development Status :: 5 - Production/Stable
Classifier: Intended Audience :: Science/Research
Classifier: Operating System :: OS Independent
Classifier: Programming Language :: Python :: 3.9
Classifier: Programming Language :: Python :: 3.10
Classifier: Programming Language :: Python :: 3.11
Classifier: Programming Language :: Python :: 3.12
Classifier: Programming Language :: Python :: 3.13
Classifier: Topic :: Scientific/Engineering :: Physics
License-File: LICENSE.txt
Requires-Dist: numpy>=1.21.5
Requires-Dist: packaging>=21.3
Requires-Dist: scipy>=1.8.0
Requires-Dist: setuptools>=44.1.1
Requires-Dist: sympy>=1.9
Provides-Extra: doc
Requires-Dist: jupyter_sphinx>=0.3.2; extra == "doc"
Requires-Dist: numpydoc>=1.2; extra == "doc"
Requires-Dist: pythreejs; extra == "doc"
Requires-Dist: sphinx>=4.3.2; extra == "doc"
Provides-Extra: codegen
Requires-Dist: Cython>=0.29.28; extra == "codegen"
Requires-Dist: Theano>=1.0.5; extra == "codegen"
Provides-Extra: examples
Requires-Dist: matplotlib>=3.5.1; extra == "examples"
Requires-Dist: notebook<5.0.0,>=4.0.0; extra == "examples"
Requires-Dist: ipywidgets<5.0.0,>=4.0.0; extra == "examples"
Dynamic: author
Dynamic: author-email
Dynamic: classifier
Dynamic: description
Dynamic: home-page
Dynamic: keywords
Dynamic: license
Dynamic: license-file
Dynamic: provides-extra
Dynamic: requires-dist
Dynamic: summary
